pynumeca/__init__.py
pynumeca/__main__.py
pynumeca/constants.py
pynumeca/fine/__init__.py
pynumeca/fine/fine.py
pynumeca/fine/utils.py
pynumeca/igg/__init__.py
pynumeca/igg/igg.py
pynumeca/igg/utils.py
pynumeca/postprocessing/__init__.py
pynumeca/postprocessing/d3d.py
pynumeca/postprocessing/mf.py
pynumeca/postprocessing/plan.py
pynumeca/postprocessing/res.py
pynumeca/preprocessing/__init__.py
pynumeca/preprocessing/bezier3d.py
pynumeca/preprocessing/bezier_geomturbo.py
pynumeca/preprocessing/turbo.py
pynumeca/pynumeca.py
pynumeca/reader/__init__.py
pynumeca/reader/geomturbo.py
pynumeca/reader/iecEntry.py
pynumeca/reader/iecGroup.py
pynumeca/reader/niBladeGeometryEntry.py
pynumeca/reader/numecaEntry.py
pynumeca/reader/numecaParser.py
pynumeca/reader/sectionEntry.py
pynumeca/reader/zrCurveEntry.py
pynumeca/utils/__init__.py
pynumeca/utils/boundaries.py
pynumeca/utils/geometric.py
pynumeca/utils/units.py
pynumeca-0.0.43.dist-info/LICENSE
pynumeca-0.0.43.dist-info/METADATA
pynumeca-0.0.43.dist-info/WHEEL
pynumeca-0.0.43.dist-info/RECORD
