Metadata-Version: 2.1
Name: pynumeca
Version: 0.0.43
Summary: Python interface to Numera family software
License: MIT
Author: GitMarco27
Author-email: marco.sanguineti.info@gmail.com
Requires-Python: >=3.9,<3.12
Classifier: License :: OSI Approved :: MIT License
Classifier: Programming Language :: Python :: 3
Classifier: Programming Language :: Python :: 3.9
Classifier: Programming Language :: Python :: 3.10
Classifier: Programming Language :: Python :: 3.11
Requires-Dist: joblib (>=1.2.0,<2.0.0)
Requires-Dist: numpy (>=1.24,<2.0)
Requires-Dist: pandas (>=1.5.3,<2.0.0)
Requires-Dist: plotly (>=5.14,<6.0)
Requires-Dist: pyfluids (>=2.3.2,<3.0.0)
Requires-Dist: scipy (>=1.10.1,<2.0.0)
Requires-Dist: tqdm (>=4.65.0,<5.0.0)
